unlimited_char/__init__.py
unlimited_char/fields.py
unlimited_char/version.py
django_unlimited_char-0.0.3b1.dist-info/LICENSE
django_unlimited_char-0.0.3b1.dist-info/METADATA
django_unlimited_char-0.0.3b1.dist-info/WHEEL
django_unlimited_char-0.0.3b1.dist-info/top_level.txt
django_unlimited_char-0.0.3b1.dist-info/RECORD
